[{"id":10073273,"title":"利用股神展开营销，巴菲特将登上可口可乐饮料罐","desc":"可口可乐2017年3月10日在中国推出了樱桃味可乐，根据该公司网站，将限时提供有巴菲特形象的罐装可乐。","outline":"可口可乐公司将把巴菲特的形象印在在中国出售的樱桃味可乐的包装上\n“没有任何证据让我确信，如果我突然改喝水、吃西兰花，我活到100岁的可能性会更大”","level":0,"inputTime":1491316369,"updateTime":1491377206,"onlineTime":0,"thumb":"http://s.qiniu.bb.bbwc.cn/issue_1265/category/2017/0404/58e3af9215f23_140x140.jpeg","webUrl":"http://read.bbwc.cn/kaiacc.html","pageUrl":"http://content.cdn.bb.bbwc.cn/v5/app1/issue_1265/articles/10073273/show-1-6-1265-13-10073273-1_1491377206.html","catName":"智趣生活,今日焦点,公司与产业,","groupName":"cat_13","sort":"10000","titleColor":"000000"},{"id":10073220,"title":"伦敦豪宅挂牌两年无买家，为求更高回报业主转向短租市场","desc":"为在房地产市场低迷的当下保证收入，伦敦的豪宅所有者正在转向爱彼迎等公司。","outline":"伦敦最昂贵地段的长期租金在一年里下跌了5.1%\n“脱欧公投以来，长租市场需求一直不是很强” ","level":0,"inputTime":1491274406,"updateTime":1491276788,"onlineTime":1491274425,"thumb":"http://s.qiniu.bb.bbwc.cn/issue_1261/category/2017/0331/58ddfe24e1595_140x140.gif","webUrl":"http://read.bbwc.cn/gmqw3s.html","pageUrl":"http://content.cdn.bb.bbwc.cn/v5/app1/issue_1261/articles/10073220/show-1-6-1261-19-10073220-1_1491276788.html","catName":"今日焦点,全球&港澳台,智趣生活,房地产","groupName":"cat_19","sort":"10000","titleColor":"000000"},{"id":10072914,"title":"求职季找工作的取舍难题：求职容易，涨薪不易","desc":"几乎所有国家的失业率都在下降，可是任何国家的工资都不上涨。","outline":"失业率接近充分就业水平，不过工资滞后\n强劲就业需求和工资上涨的良性循环难以实现","level":0,"inputTime":1491260458,"updateTime":1491029919,"onlineTime":1491260458,"thumb":"http://s.qiniu.bb.bbwc.cn/issue_1256/category/2017/0316/58ca6a85bc67b_140x140.gif","webUrl":"http://read.bbwc.cn/5rxran.html","pageUrl":"http://content.cdn.bb.bbwc.cn/v5/app1/issue_1256/articles/10072914/show-1-6-1256-19-10072914-1_1491029919.html","catName":"全球&港澳台,智趣生活","groupName":"cat_19","sort":"10000","titleColor":"000000"},{"id":10073158,"title":"高管患“精疲力竭综合征”，强生推出10万美元高管拯救计划","desc":"弥补CEO突然辞职导致的职位空缺，美国企业平均要损耗18亿美元的股东价值。","outline":"高管人员将得到专家的全方位细致呵护\n“你做不到将生活和工作分开。人们在开始某项事情之前，往往不会做自我检查”","level":1,"inputTime":1491260436,"updateTime":1491040301,"onlineTime":1491260424,"thumb":"http://s.qiniu.bb.bbwc.cn/issue_1261/category/2017/0329/58da9b2f2943d_140x140.gif","webUrl":"http://read.bbwc.cn/wahwky.html","pageUrl":"http://content.cdn.bb.bbwc.cn/v5/app1/issue_1261/articles/10073158/show-1-6-1261-20-10073158-1_1491040301.html","catName":"公司与产业,今日焦点,智趣生活","groupName":"cat_20","sort":"10000","titleColor":"000000"},{"id":10073242,"title":"沃尔特·惠特曼的健康忠告：健康是一笔长期投资","desc":"他的一些建议提炼成令人难忘的格言警句，全书散发着这位留着胡须的纽约布鲁克林人对男性打扮的真知灼见。","outline":"从赚钱的角度来看，健康是一笔比任何东西都好的投资\n“中年岁月不仅应该是你的事业高峰，也应该是你最帅气的时期”","level":0,"inputTime":1491187092,"updateTime":1491044566,"onlineTime":1491187092,"thumb":"http://s.qiniu.bb.bbwc.cn/issue_1261/category/2017/0401/58df1cdc5c802_140x140.gif","webUrl":"http://read.bbwc.cn/oxxc1b.html","pageUrl":"http://content.cdn.bb.bbwc.cn/v5/app1/issue_1261/articles/10073242/show-1-6-1261-13-10073242-1_1491044566.html","catName":"智趣生活","groupName":"cat_13","sort":"10000","titleColor":"000000"},{"id":10073263,"title":"卖里程比卖机票更赚，到底什么是航空公司的现金牛和摇钱树？","desc":"航空公司的摇钱树并不是机票或行李托运费，而是旅客用来兑换常飞里程的信用卡。","outline":"获得里程而支付相关信用卡年费的持卡人是最接近于“稳赚不赔”的买卖\n“在经济衰退时期，这种与银行合作的业务将会下滑，但仍会为航空公司提供很大的缓冲效应”","level":0,"inputTime":1491101862,"updateTime":1491044877,"onlineTime":1491101871,"thumb":"http://s.qiniu.bb.bbwc.cn/issue_1261/category/2017/0401/58df89a60e570_140x140.gif","webUrl":"http://read.bbwc.cn/bmqhgh.html","pageUrl":"http://content.cdn.bb.bbwc.cn/v5/app1/issue_1261/articles/10073263/show-1-6-1261-13-10073263-1_1491044877.html","catName":"智趣生活","groupName":"cat_13","sort":"10000","titleColor":"000000"},{"id":10073236,"title":"机器人将加入达美乐送餐大军，或缓解未来外卖员紧缺现象","desc":"全球第二大披萨连锁集团达美乐将在荷兰、德国的部分城市提供无人车送餐服务。","outline":"达美乐公司一直在强调顾客订购比萨的各种方式\n“如果不用这样的措施增加外送的队伍，外卖员将出现紧缺”","level":0,"inputTime":1490955083,"updateTime":1491010934,"onlineTime":0,"thumb":"http://s.qiniu.bb.bbwc.cn/issue_1261/category/2017/0331/58de2beb025d4_140x140.jpeg","webUrl":"http://read.bbwc.cn/zx2dhw.html","pageUrl":"http://content.cdn.bb.bbwc.cn/v5/app1/issue_1261/articles/10073236/show-1-6-1261-13-10073236-1_1491010934.html","catName":"智趣生活","groupName":"cat_13","sort":"10000","titleColor":"000000"},{"id":10073232,"title":"“代理第一夫人”伊万卡，违反“铁律”插手“白宫厨房”事务","desc":"风姿绰约的伊万卡宣布“不会过多参与和‘白宫厨房’有关的事务”，却涉嫌违反了白宫一条“铁律”—“白宫厨房”及和厨房有关的一切。","outline":"白宫的厨房、草坪、花园，都是总统伴侣们履行自己职责的地方\n从厨房到果蔬园，不仅关系到的是总统政要的口腹，更是白宫女眷们的理念发挥力量的舞台","level":0,"inputTime":1490950164,"updateTime":1491016198,"onlineTime":0,"thumb":"http://s.qiniu.bb.bbwc.cn/issue_1261/category/2017/0331/58de1825e7eb0_140x140.jpg","webUrl":"http://read.bbwc.cn/sw3njc.html","pageUrl":"http://content.cdn.bb.bbwc.cn/v5/app1/issue_1261/articles/10073232/show-1-6-1261-13-10073232-1_1491016198.html","catName":"智趣生活","groupName":"cat_13","sort":"10000","titleColor":"000000"},{"id":10073195,"title":"L2调查报告，中国游客海外消费刺激品牌开启数字营销策略","desc":"目前各大奢侈品品牌已经普遍开始使用多渠道策略，以促进中国游客的需求。","outline":"对外国商品的高需求也导致了中国跨境电子商务销量激增\n品牌开始为使用支付宝的游客提供各种独家优惠政策","level":0,"inputTime":1490854049,"updateTime":1490857232,"onlineTime":0,"thumb":"http://s.qiniu.bb.bbwc.cn/issue_1261/category/2017/0330/58dcabff83d27_140x140.png","webUrl":"http://read.bbwc.cn/oyojp1.html","pageUrl":"http://content.cdn.bb.bbwc.cn/v5/app1/issue_1261/articles/10073195/show-1-6-1261-13-10073195-1_1490857232.html","catName":"智趣生活","groupName":"cat_13","sort":"10000","titleColor":"000000"},{"id":10073150,"title":"杜蕾斯牛仔裤：打破印度安全套禁忌","desc":"印度人使用安全套作为避孕措施的比率不到6%，而同时这个国家艾滋病感染人数高居世界第三。","outline":"利洁时印度公司推出“杜蕾斯牛仔裤”安全套产品\n6%的安全套使用率反映印度社会的羞耻心理","level":1,"inputTime":1490687251,"updateTime":1490721782,"onlineTime":1490687252,"thumb":"http://s.qiniu.bb.bbwc.cn/issue_1261/category/2017/0328/58da1334e252b_140x140.jpg","webUrl":"http://read.bbwc.cn/qj2ksz.html","pageUrl":"http://content.cdn.bb.bbwc.cn/v5/app1/issue_1261/articles/10073150/show-1-6-1261-20-10073150-1_1490721782.html","catName":"公司与产业,智趣生活","groupName":"cat_20","sort":"10000","titleColor":"000000"},{"id":10073118,"title":"最佳中转旅行计划，用一个假期的钱，过两个假期","desc":"冰岛航空的促进计划，是冰岛旅游业最大的催化剂。","outline":"已有约40000名游客采取了中转停留计划，而航空公司也由此重启了复兴时代\n“中转项目是我们扩张战略的核心，它让我们得以向整个北美的乘客，兜售整个欧洲”","level":0,"inputTime":1490587969,"updateTime":1490601301,"onlineTime":0,"thumb":"http://s.qiniu.bb.bbwc.cn/issue_1261/category/2017/0327/58d892105eb5c_140x140.jpeg","webUrl":"http://read.bbwc.cn/uuffsq.html","pageUrl":"http://content.cdn.bb.bbwc.cn/v5/app1/issue_1261/articles/10073118/show-1-6-1261-13-10073118-1_1490601301.html","catName":"智趣生活","groupName":"cat_13","sort":"10000","titleColor":"000000"},{"id":10073112,"title":"所谓“高雅文化”的播客，可能使你患上“错过恐惧症”","desc":"好播客太多了，但追更新的同时，也给自己带来了压力。\n","outline":"播客在2004年才开始大行其道\n它成为了富人们的必修课，而且比听音乐或广播更显知识层次","level":1,"inputTime":1490579477,"updateTime":1490580126,"onlineTime":0,"thumb":"http://s.qiniu.bb.bbwc.cn/issue_1261/category/2017/0327/58d871c58d44d_140x140.gif","webUrl":"http://read.bbwc.cn/11onqd.html","pageUrl":"http://content.cdn.bb.bbwc.cn/v5/app1/issue_1261/articles/10073112/show-1-6-1261-13-10073112-1_1490580126.html","catName":"智趣生活","groupName":"cat_13","sort":"10000","titleColor":"000000"},{"id":10073101,"title":"不吸烟、无家族遗传就不会患癌症？癌症其实和运气有关","desc":"虽然吸烟仍可以要人命，但三分之二致癌基因突变的结果如何却要看运气。\n","outline":"癌症与正常的干细胞分裂有着密切联系\n三分之二给人类带来痛苦的基因突变是“坏运气”造成的","level":0,"inputTime":1490344515,"updateTime":1490345281,"onlineTime":0,"thumb":"http://s.qiniu.bb.bbwc.cn/issue_1261/category/2017/0324/58d4dd05239f1_140x140.gif","webUrl":"http://read.bbwc.cn/lhwvkn.html","pageUrl":"http://content.cdn.bb.bbwc.cn/v5/app1/issue_1261/articles/10073101/show-1-6-1261-13-10073101-1_1490345281.html","catName":"智趣生活","groupName":"cat_13","sort":"10000","titleColor":"000000"},{"id":10073080,"title":"游客太多也是错？新西兰的旅游业竟被游客接待能力不足所拖累","desc":"游客接待能力不足的问题可能最终会拖累到新西兰最大的外汇创收部门——旅游业。","outline":"络绎不绝的游客对当地基础设施和环境构成压力\n酒店客房短缺突显投资旅游业基础设施的必要性","level":0,"inputTime":1490275252,"updateTime":1490332383,"onlineTime":0,"thumb":"http://s.qiniu.bb.bbwc.cn/issue_1261/category/2017/0323/58d3ce90e25e5_140x140.jpeg","webUrl":"http://read.bbwc.cn/wduu2f.html","pageUrl":"http://content.cdn.bb.bbwc.cn/v5/app1/issue_1261/articles/10073080/show-1-6-1261-13-10073080-1_1490332383.html","catName":"智趣生活","groupName":"cat_13","sort":"10000","titleColor":"000000"},{"id":10073010,"title":"全球最长寿的亿万富翁戴维·洛克菲勒去世，享年101岁","desc":"戴维·洛克菲勒去世，享年101岁，他是美国著名的银行家、慈善家和总统顾问，也是全球最长寿的亿万富翁。","outline":"美国传奇富豪家族的传人，世上最长寿的亿万富翁\n标准石油公司创始人约翰·洛克菲勒最小的孙子","level":0,"inputTime":1490088325,"updateTime":1490148124,"onlineTime":0,"thumb":"http://s.qiniu.bb.bbwc.cn/issue_1261/category/2017/0321/58d0f46f4ab78_140x140.jpeg","webUrl":"http://read.bbwc.cn/zosffq.html","pageUrl":"http://content.cdn.bb.bbwc.cn/v5/app1/issue_1261/articles/10073010/show-1-6-1261-13-10073010-1_1490148124.html","catName":"智趣生活,特写","groupName":"cat_13","sort":"10000","titleColor":"000000"},{"id":10072995,"title":"神奇的收视率：视频网站的收视率能信几成？","desc":"统计显示《三生三世十里桃花》网络日播放量超过15亿次，如此量级被戏谑调侃为“中国人口最近几天严重不够用了”。","outline":"“网络播放量”概念模糊，且不同视频网站计数标准不统一\n“如果用户一点击就计数，很难排除用户误点的情况”","level":1,"inputTime":1490067600,"updateTime":1490069619,"onlineTime":0,"thumb":"http://s.qiniu.bb.bbwc.cn/issue_1261/category/2017/0321/58d0a2cca1bba_140x140.gif","webUrl":"http://read.bbwc.cn/mgjzdf.html","pageUrl":"http://content.cdn.bb.bbwc.cn/v5/app1/issue_1261/articles/10072995/show-1-6-1261-13-10072995-1_1490069619.html","catName":"智趣生活","groupName":"cat_13","sort":"10000","titleColor":"000000"},{"id":10072955,"title":"专访艾玛•沃特森：超前时代公主魅力","desc":"它的出现代表了这个消费时代的现状：经典永远需要被消费和传承，而人们对于新鲜感的要求愈发迫切。","outline":"沃特森曾经认真地考虑过放弃演艺事业，甚至从此远离好莱坞\n“拍完《美女与野兽》之后，我真切地感到自己在银幕上也成为了女人”","level":0,"inputTime":1489745260,"updateTime":1489745750,"onlineTime":1489745260,"thumb":"http://s.qiniu.bb.bbwc.cn/issue_1256/category/2017/0317/58cbb47f77781_140x140.jpg","webUrl":"http://read.bbwc.cn/3nomw3.html","pageUrl":"http://content.cdn.bb.bbwc.cn/v5/app1/issue_1256/articles/10072955/show-1-6-1256-13-10072955-1_1489745750.html","catName":"智趣生活","groupName":"cat_13","sort":"10000","titleColor":"000000"},{"id":10072953,"title":"不愿删减同性恋情节 《美女与野兽》推迟在马来西亚上映","desc":"制片方决定将影片的上映时间无限期推迟，称不会为任何国家删减影片。","outline":"制片方决定将影片的上映时间无限期推迟，称不会为任何国家删减影片\n重制版《美女与野兽》票房收入预计将在上映后第一个周末达1.2亿美元","level":0,"inputTime":1489741531,"updateTime":1489742172,"onlineTime":1489742081,"thumb":"http://s.qiniu.bb.bbwc.cn/issue_1256/category/2017/0317/58cba8185c27f_140x140.png","webUrl":"http://read.bbwc.cn/ob3xqk.html","pageUrl":"http://content.cdn.bb.bbwc.cn/v5/app1/issue_1256/articles/10072953/show-1-6-1256-13-10072953-1_1489742172.html","catName":"智趣生活","groupName":"cat_13","sort":"10000","titleColor":"000000"},{"id":10072944,"title":"希望能继承一笔遗产的你，可能拿不到期待中的那么多","desc":"所有人在拿到遗产时都会心怀感激，也没有哪个父母想在自己去世后什么都没给后代留下。","outline":"对于父母来说，有时候问题在于，遗产分配到底是该合理，还是该平均\n通过设定适当的预期，遗产的继承“将不大会成为日后家庭矛盾的根源”\n","level":1,"inputTime":1489731247,"updateTime":1492424050,"onlineTime":0,"thumb":"http://s.qiniu.bb.bbwc.cn/issue_1256/category/2017/0317/58cb8061ac3dc_140x140.jpg","webUrl":"http://read.bbwc.cn/r2sdg3.html","pageUrl":"http://content.cdn.bb.bbwc.cn/v5/app1/issue_1256/articles/10072944/show-1-6-1256-13-10072944-1_1492424050.html","catName":"智趣生活,读·报","groupName":"cat_13","sort":"10000","titleColor":"000000"},{"id":10072885,"title":"史密森尼学会年度最佳全球旅行照片","desc":"评奖者可以在入围决赛的近70张照片中投票选出自己喜爱的照片，这些照片的类型包括人物、美国故事、变幻的形象、环保旅行等7类。","outline":"评奖者可以在入围决赛的近70张照片中投票选出自己喜爱的照片\n投票截止到美国东部标准时间2017年3月27日晚上11点59分，获奖名单将于3月28日公布","level":0,"inputTime":1489566273,"updateTime":1489566449,"onlineTime":1489566273,"thumb":"http://s.qiniu.bb.bbwc.cn/issue_1256/category/2017/0315/58c8f95b58860_140x140.jpg","webUrl":"http://read.bbwc.cn/yggchh.html","pageUrl":"http://content.cdn.bb.bbwc.cn/v5/app1/issue_1256/articles/10072885/show-1-6-1256-13-10072885-1_1489566449.html","catName":"智趣生活","groupName":"cat_13","sort":"10000","titleColor":"000000"}]